emdcmp/__init__.py
emdcmp/_version.py
emdcmp/digitize.py
emdcmp/emd.md
emdcmp/emd.py
emdcmp/memoize.py
emdcmp/path_sampling.md
emdcmp/path_sampling.py
emdcmp/tasks.md
emdcmp/tasks.py
emdcmp/utils.py
emdcmp/viz.md
emdcmp/viz.py
emdcmp/config/__init__.md
emdcmp/config/__init__.py
emdcmp/config/defaults.cfg
emdcmp-1.1.1.dist-info/licenses/LICENSE
emdcmp-1.1.1.dist-info/METADATA
emdcmp-1.1.1.dist-info/WHEEL
emdcmp-1.1.1.dist-info/top_level.txt
emdcmp-1.1.1.dist-info/RECORD
